alakazam/__init__.py
alakazam/anonymous.py
alakazam/error.py
alakazam/lift.py
alakazam/trace.py
alakazam/util.py
alakazam-0.7.0.dist-info/DESCRIPTION.rst
alakazam-0.7.0.dist-info/METADATA
alakazam-0.7.0.dist-info/RECORD
alakazam-0.7.0.dist-info/WHEEL
alakazam-0.7.0.dist-info/metadata.json
alakazam-0.7.0.dist-info/top_level.txt
