Metadata-Version: 2.0
Name: alakazam
Version: 0.7.0
Summary: Functional programming sugar for Python
Home-page: https://github.com/Mercerenies/alakazam
Author: Silvio Mayolo
Author-email: mercerenies@comcast.net
License: BSD3
Download-URL: https://github.com/Mercerenies/alakazam/archive/0.7.0.tar.gz
Keywords: functional,sugar,syntax,lambda,stream,alakazam
Platform: UNKNOWN
Classifier: Development Status :: 3 - Alpha
Classifier: Intended Audience :: Developers
Classifier: Topic :: Software Development :: Libraries :: Python Modules
Classifier: License :: OSI Approved :: BSD License
Classifier: Programming Language :: Python :: 2
Classifier: Programming Language :: Python :: 2.6
Classifier: Programming Language :: Python :: 2.7
Classifier: Programming Language :: Python :: 3
Classifier: Programming Language :: Python :: 3.2
Classifier: Programming Language :: Python :: 3.3
Classifier: Programming Language :: Python :: 3.4
Classifier: Programming Language :: Python :: 3.5
Classifier: Programming Language :: Python :: 3.6
